{
  "run": {
    "command": "nx run auth-service:start:dev",
    "startTime": "2023-12-13T14:45:35.260Z",
    "endTime": "2023-12-13T17:44:44.429Z",
    "inner": false
  },
  "tasks": [
    {
      "taskId": "auth-service:start:dev",
      "target": "start:dev",
      "projectName": "auth-service",
      "hash": "10958443587557889795",
      "startTime": "2023-12-13T14:45:35.267Z",
      "endTime": "2023-12-13T17:44:44.421Z",
      "params": "",
      "cacheStatus": "cache-miss",
      "status": 1
    }
  ]
}